[[{"time":"20 საათი","temperature":5,"weather":"მოწმენდილი"},{"time":"21 საათი","temperature":4,"weather":"მოწმენდილი"},{"time":"22 საათი","temperature":3,"weather":"მოწმენდილი"},{"time":"23 საათი","temperature":3,"weather":"მოწმენდილი"},{"time":"0 საათი","temperature":2,"weather":"მოწმენდილი"},{"time":"1 საათი","temperature":2,"weather":"მოწმენდილი"},{"time":"2 საათი","temperature":2,"weather":"მოწმენდილი"},{"time":"3 საათი","temperature":1,"weather":"მოწმენდილი"},{"time":"4 საათი","temperature":1,"weather":"მოწმენდილი"},{"time":"5 საათი","temperature":1,"weather":"მოწმენდილი"},{"time":"6 საათი","temperature":1,"weather":"მოწმენდილი"},{"time":"7 საათი","temperature":0,"weather":"მოწმენდილი"},{"time":"8 საათი","temperature":0,"weather":"მზიანი"},{"time":"9 საათი","temperature":1,"weather":"მზიანი"},{"time":"10 საათი","temperature":2,"weather":"მზიანი"},{"time":"11 საათი","temperature":4,"weather":"მზიანი"},{"time":"12 საათი","temperature":6,"weather":"მზიანი"},{"time":"13 საათი","temperature":7,"weather":"მზიანი"},{"time":"14 საათი","temperature":9,"weather":"უმეტესად მზიანი"},{"time":"15 საათი","temperature":10,"weather":"ნაწილობრივ მზიანი"},{"time":"16 საათი","temperature":9,"weather":"უმეტესად ღრუბლიანი"},{"time":"17 საათი","temperature":8,"weather":"უმეტესად ღრუბლიანი"},{"time":"18 საათი","temperature":7,"weather":"ღრუბლიანი"},{"time":"19 საათი","temperature":6,"weather":"ღრუბლიანი"}]]